{
  "recentFiles": [
    {
      "basename": "Base de um espaço",
      "path": "Notes/Base de um espaço.md"
    },
    {
      "basename": "README",
      "path": "README.md"
    },
    {
      "basename": "Método da posição falsa",
      "path": "Notes/Método da posição falsa.md"
    },
    {
      "basename": "Vetores geradores de subespaço",
      "path": "Notes/Vetores geradores de subespaço.md"
    },
    {
      "basename": "Sistemas lineares",
      "path": "Notes/Sistemas lineares.md"
    },
    {
      "basename": "Teorema de Rouché-Capelli",
      "path": "Notes/Teorema de Rouché-Capelli.md"
    },
    {
      "basename": "Forma vetorial de sistemas lineares",
      "path": "Notes/Forma vetorial de sistemas lineares.md"
    },
    {
      "basename": "Álgebra Linear",
      "path": "Notes/Álgebra Linear.md"
    },
    {
      "basename": "Método de bissecção",
      "path": "Notes/Método de bissecção.md"
    },
    {
      "basename": "Método da secante",
      "path": "Notes/Método da secante.md"
    },
    {
      "basename": "Método de Newton-Raphson (tangente)",
      "path": "Notes/Método de Newton-Raphson (tangente).md"
    },
    {
      "basename": "Métodos iterativos",
      "path": "Notes/Métodos iterativos.md"
    },
    {
      "basename": "Método do ponto fixo",
      "path": "Notes/Método do ponto fixo.md"
    },
    {
      "basename": "Método de Petrick",
      "path": "Notes/Método de Petrick.md"
    },
    {
      "basename": "Sem título 1",
      "path": "Notes/Sem título 1.md"
    },
    {
      "basename": "Integral de linha",
      "path": "Notes/Integral de linha.md"
    },
    {
      "basename": "Diferencial de volume",
      "path": "Notes/Diferencial de volume.md"
    },
    {
      "basename": "Diferencial de área",
      "path": "Notes/Diferencial de área.md"
    },
    {
      "basename": "Diferencial de deslocamento",
      "path": "Notes/Diferencial de deslocamento.md"
    },
    {
      "basename": "Geometria analítica",
      "path": "Notes/Geometria analítica.md"
    },
    {
      "basename": "Estudo de convergência do método da bissecção",
      "path": "Notes/Estudo de convergência do método da bissecção.md"
    },
    {
      "basename": "Estimativa do número de iterações",
      "path": "Notes/Estimativa do número de iterações.md"
    },
    {
      "basename": "Teorema fundamental da álgebra (TFA)",
      "path": "Notes/Teorema fundamental da álgebra (TFA).md"
    },
    {
      "basename": "Método de Quine-McCluskey",
      "path": "Notes/Método de Quine-McCluskey.md"
    },
    {
      "basename": "Algebra de Boole",
      "path": "Notes/Algebra de Boole.md"
    },
    {
      "basename": "Portas lógicas",
      "path": "Notes/Portas lógicas.md"
    },
    {
      "basename": "Mapa de Karnaugh",
      "path": "Notes/Mapa de Karnaugh.md"
    },
    {
      "basename": "Introdução de variável no mapa de Karnaugh",
      "path": "Notes/Introdução de variável no mapa de Karnaugh.md"
    },
    {
      "basename": "Maxtermos",
      "path": "Notes/Maxtermos.md"
    },
    {
      "basename": "Coordenadas esféricas",
      "path": "Notes/Coordenadas esféricas.md"
    },
    {
      "basename": "Coordenadas cilíndricas",
      "path": "Notes/Coordenadas cilíndricas.md"
    },
    {
      "basename": "Cálculo diferencial",
      "path": "Notes/Cálculo diferencial.md"
    },
    {
      "basename": "Coordenadas cartesianas",
      "path": "Notes/Coordenadas cartesianas.md"
    },
    {
      "basename": "Geometria",
      "path": "Notes/Geometria.md"
    },
    {
      "basename": "Teorema do ponto fixo de Brouler",
      "path": "Notes/Teorema do ponto fixo de Brouler.md"
    },
    {
      "basename": "Teorema do valor intermediário (TVI)",
      "path": "Notes/Teorema do valor intermediário (TVI).md"
    },
    {
      "basename": "Ponto fixo",
      "path": "Notes/Ponto fixo.md"
    },
    {
      "basename": "Zero de funções reais",
      "path": "Notes/Zero de funções reais.md"
    },
    {
      "basename": "Campo eletromagnético",
      "path": "Notes/Campo eletromagnético.md"
    },
    {
      "basename": "Sistemas digitais",
      "path": "Notes/Sistemas digitais.md"
    },
    {
      "basename": "Porta NOT",
      "path": "Notes/Porta NOT.md"
    },
    {
      "basename": "Teorema de DeMorgan",
      "path": "Notes/Teorema de DeMorgan.md"
    },
    {
      "basename": "Porta XNOR",
      "path": "Notes/Porta XNOR.md"
    },
    {
      "basename": "Porta XOR",
      "path": "Notes/Porta XOR.md"
    },
    {
      "basename": "Porta NOR",
      "path": "Notes/Porta NOR.md"
    },
    {
      "basename": "Porta NAND",
      "path": "Notes/Porta NAND.md"
    },
    {
      "basename": "Porta OR",
      "path": "Notes/Porta OR.md"
    },
    {
      "basename": "Porta AND",
      "path": "Notes/Porta AND.md"
    },
    {
      "basename": "Delta de Dirac",
      "path": "Notes/Delta de Dirac.md"
    },
    {
      "basename": "Sinal impulso unitário",
      "path": "Notes/Sinal impulso unitário.md"
    }
  ],
  "omittedPaths": [],
  "maxLength": null,
  "openType": "tab"
}